__init__.py
agent.py
cli_parser.py
command_processor.py
config.py
hashtagai.py
helpfunc.py
history_manager.py
interactive_mode.py
model_init.py
system_info.py
hashtagai-0.3.0.dist-info/METADATA
hashtagai-0.3.0.dist-info/WHEEL
hashtagai-0.3.0.dist-info/entry_points.txt
hashtagai-0.3.0.dist-info/top_level.txt
hashtagai-0.3.0.dist-info/RECORD
